paranumpy/__init__.py
paranumpy/paranumpy.py
paranumpy-1.0.2.dist-info/LICENCE
paranumpy-1.0.2.dist-info/METADATA
paranumpy-1.0.2.dist-info/WHEEL
paranumpy-1.0.2.dist-info/top_level.txt
paranumpy-1.0.2.dist-info/RECORD
