Metadata-Version: 2.1
Name: paranumpy
Version: 1.0.2
Summary: A collection of functions for the parallel handling of numpy arrays
Home-page: https://github.com/cs2t/paranumpy
Author: Fabio Caruso
Author-email: caruso@physik.uni-kiel.de
License: UNKNOWN
Platform: UNKNOWN
Classifier: Programming Language :: Python :: 3
Classifier: License :: OSI Approved :: MIT License
Classifier: Operating System :: OS Independent
Requires-Python: >=3.6
Requires-Dist: numpy
Requires-Dist: mpi4py
